{
  "file_name": "celebi_2019_guest_editorial_skin_lesion_image_analysis_for_melanoma_detection.json",
  "did_this_paper_use_ai_to_obtain_results_in_dermatology": {
    "answer": "Yes",
    "details": "The paper is a guest editorial summarizing a special issue on skin lesion image analysis for melanoma detection. It explicitly states that 42% of the articles in the issue are related to deep learning. It details the use of various AI and computational methods including convolutional-deconvolutional neural networks (CDNN), dense deconvolutional neural networks, fully convolutional neural networks (VGG16), multi-task multi-modal neural nets, active contour models, superpixel-based segmentation, and color detection algorithms using k-means clustering and quadtree decomposition for tasks such as segmentation, feature extraction, and classification of dermoscopic images."
  },
  "is_this_paper_a_review_paper_or_a_research_paper": {
    "answer": "Review paper",
    "details": "The document is explicitly titled 'Guest Editorial' and serves to summarize the state-of-the-art in a special issue on skin lesion image analysis. It describes the contents of 12 accepted papers, categorizing them by topic (segmentation, feature extraction, classification, registration) and summarizing their methodologies, rather than presenting original experimental results from the authors themselves."
  },
  "non_compliance_reason": "The paper is a review, survey, or meta-analysis rather than an original research paper."
}
