{
  "file_name": "chopade_2019_classification_of_skin_lesions_by_using_extended_incremental_convol.json",
  "did_this_paper_use_ai_to_obtain_results_in_dermatology": {
    "answer": "No",
    "details": "The paper discusses an efficient hybrid decoder for block turbo codes in the context of telecommunications (BPSK modulation over AWGN channels), not dermatology or skin cancer. It does not use AI, machine learning, or deep learning for dermatological results."
  },
  "non_compliance_reason": "The paper does not use AI to obtain results in dermatology."
}
